specimen/__init__.py
specimen/file.py
specimen/flag.py
specimen/focustree/__init__.py
specimen/focustree/focustree.py
specimen/nodule.py
specimen/run.py
specimen/spec_test.py
specimen/syaml/__init__.py
specimen/syaml/check.py
specimen/syaml/map.py
specimen-0.1.0.dist-info/METADATA
specimen-0.1.0.dist-info/WHEEL
specimen-0.1.0.dist-info/RECORD
